pyro/__init__.py
pyro/_defaults
pyro/_version.py
pyro/compare.py
pyro/inputs.auto
pyro/inputs.convection.big
pyro/inputs.convection.big~
pyro/inputs.convection.small
pyro/inputs.convection~
pyro/plot.py
pyro/pyro_sim.py
pyro/simulation_null.py
pyro/test.py
pyro/advection/__init__.py
pyro/advection/_defaults
pyro/advection/advective_fluxes.py
pyro/advection/interface.py
pyro/advection/simulation.py
pyro/advection/problems/__init__.py
pyro/advection/problems/inputs.smooth
pyro/advection/problems/inputs.tophat
pyro/advection/problems/smooth.py
pyro/advection/problems/test.py
pyro/advection/problems/tophat.py
pyro/advection/tests/smooth_0040.h5
pyro/advection_fv4/__init__.py
pyro/advection_fv4/_defaults
pyro/advection_fv4/fluxes.py
pyro/advection_fv4/simulation.py
pyro/advection_fv4/problems/__init__.py
pyro/advection_fv4/problems/inputs.smooth
pyro/advection_fv4/problems/inputs.tophat
pyro/advection_fv4/problems/smooth.py
pyro/advection_fv4/problems/test.py
pyro/advection_fv4/problems/tophat.py
pyro/advection_fv4/tests/smooth_0081.h5
pyro/advection_nonuniform/__init__.py
pyro/advection_nonuniform/_defaults
pyro/advection_nonuniform/advective_fluxes.py
pyro/advection_nonuniform/simulation.py
pyro/advection_nonuniform/problems/__init__.py
pyro/advection_nonuniform/problems/inputs.slotted
pyro/advection_nonuniform/problems/slotted.py
pyro/advection_nonuniform/problems/test.py
pyro/advection_nonuniform/tests/slotted_0248.h5
pyro/advection_rk/__init__.py
pyro/advection_rk/_defaults
pyro/advection_rk/fluxes.py
pyro/advection_rk/simulation.py
pyro/advection_rk/problems/__init__.py
pyro/advection_rk/problems/inputs.smooth
pyro/advection_rk/problems/inputs.tophat
pyro/advection_rk/problems/smooth.py
pyro/advection_rk/problems/test.py
pyro/advection_rk/problems/tophat.py
pyro/advection_rk/tests/smooth_0081.h5
pyro/advection_weno/__init__.py
pyro/advection_weno/_defaults
pyro/advection_weno/fluxes.py
pyro/advection_weno/simulation.py
pyro/advection_weno/problems/__init__.py
pyro_hydro-4.5.0.dist-info/LICENSE
pyro_hydro-4.5.0.dist-info/METADATA
pyro_hydro-4.5.0.dist-info/WHEEL
pyro_hydro-4.5.0.dist-info/entry_points.txt
pyro_hydro-4.5.0.dist-info/top_level.txt
pyro_hydro-4.5.0.dist-info/RECORD
