Metadata-Version: 2.2
Name: pyro-hydro
Version: 4.5.0
Summary: A python hydrodynamics code for teaching and prototyping
Author: pyro development group
Author-email: michael.zingale@stonybrook.edu
License: BSD
Project-URL: Homepage, https://github.com/python-hydro/pyro2
Project-URL: Documentation, https://python-hydro.github.io/pyro2
License-File: LICENSE
Requires-Dist: numba
Requires-Dist: numpy
Requires-Dist: matplotlib
Requires-Dist: h5py
